/*     */ package examples.ftp;
/*     */ 
/*     */ import java.io.PrintStream;
/*     */ import org.apache.commons.net.io.CopyStreamEvent;
/*     */ import org.apache.commons.net.io.CopyStreamListener;
/*     */ 
/*     */ public final class FTPClientExample
/*     */ {
/*     */   public static final String USAGE = "Usage: ftp [options] <hostname> <username> <password> [<remote file> [<local file>]]\n\nDefault behavior is to download a file and use ASCII transfer mode.\n\t-a - use local active mode (default is local passive)\n\t-b - use binary transfer mode\n\t-c cmd - issue arbitrary command (remote is used as a parameter if provided) \n\t-d - list directory details using MLSD (remote is used as the pathname if provided)\n\t-e - use EPSV with IPv4 (default false)\n\t-f - issue FEAT command (remote and local files are ignored)\n\t-h - list hidden files (applies to -l and -n only)\n\t-k secs - use keep-alive timer (setControlKeepAliveTimeout)\n\t-l - list files using LIST (remote is used as the pathname if provided)\n\t-L - use lenient future dates (server dates may be up to 1 day into future)\n\t-n - list file names using NLST (remote is used as the pathname if provided)\n\t-p true|false|protocol[,true|false] - use FTPSClient with the specified protocol and/or isImplicit setting\n\t-s - store file on server (upload)\n\t-t - list file details using MLST (remote is used as the pathname if provided)\n\t-w msec - wait time for keep-alive reply (setControlKeepAliveReplyTimeout)\n\t-T  all|valid|none - use one of the built-in TrustManager implementations (none = JVM default)\n\t-# - add hash display during transfers\n";
/*     */   
/*     */   /* Error */
/*     */   public static final void main(String[] args)
/*     */   {
/*     */     // Byte code:
/*     */     //   0: iconst_0
/*     */     //   1: istore_1
/*     */     //   2: iconst_0
/*     */     //   3: istore_2
/*     */     //   4: iconst_0
/*     */     //   5: istore_3
/*     */     //   6: iconst_0
/*     */     //   7: istore 4
/*     */     //   9: iconst_0
/*     */     //   10: istore 5
/*     */     //   12: iconst_0
/*     */     //   13: istore 6
/*     */     //   15: iconst_0
/*     */     //   16: istore 7
/*     */     //   18: iconst_0
/*     */     //   19: istore 8
/*     */     //   21: iconst_0
/*     */     //   22: istore 9
/*     */     //   24: iconst_0
/*     */     //   25: istore 10
/*     */     //   27: iconst_0
/*     */     //   28: istore 11
/*     */     //   30: iconst_0
/*     */     //   31: istore 12
/*     */     //   33: iconst_0
/*     */     //   34: istore 13
/*     */     //   36: ldc2_w 21
/*     */     //   39: lstore 14
/*     */     //   41: iconst_m1
/*     */     //   42: istore 16
/*     */     //   44: iconst_5
/*     */     //   45: istore 17
/*     */     //   47: aconst_null
/*     */     //   48: astore 18
/*     */     //   50: aconst_null
/*     */     //   51: astore 19
/*     */     //   53: aconst_null
/*     */     //   54: astore 20
/*     */     //   56: iconst_0
/*     */     //   57: istore 21
/*     */     //   59: iconst_0
/*     */     //   60: istore 21
/*     */     //   62: goto +361 -> 423
/*     */     //   65: aload_0
/*     */     //   66: iload 21
/*     */     //   68: aaload
/*     */     //   69: ldc 23
/*     */     //   71: invokevirtual 25	java/lang/String:equals	(Ljava/lang/Object;)Z
/*     */     //   74: ifeq +8 -> 82
/*     */     //   77: iconst_1
/*     */     //   78: istore_1
/*     */     //   79: goto +341 -> 420
/*     */     //   82: aload_0
/*     */     //   83: iload 21
/*     */     //   85: aaload
/*     */     //   86: ldc 31
/*     */     //   88: invokevirtual 25	java/lang/String:equals	(Ljava/lang/Object;)Z
/*     */     //   91: ifeq +9 -> 100
/*     */     //   94: iconst_1
/*     */     //   95: istore 7
/*     */     //   97: goto +323 -> 420
/*     */     //   100: aload_0
/*     */     //   101: iload 21
/*     */     //   103: aaload
/*     */     //   104: ldc 33
/*     */     //   106: invokevirtual 25	java/lang/String:equals	(Ljava/lang/Object;)Z
/*     */     //   109: ifeq +8 -> 117
/*     */     //   112: iconst_1
/*     */     //   113: istore_2
/*     */     //   114: goto +306 -> 420
/*     */     //   117: aload_0
/*     */     //   118: iload 21
/*     */     //   120: aaload
/*     */     //   121: ldc 35
/*     */     //   123: invokevirtual 25	java/lang/String:equals	(Ljava/lang/Object;)Z
/*     */     //   126: ifeq +18 -> 144
/*     */     //   129: aload_0
/*     */     //   130: iinc 21 1
/*     */     //   133: iload 21
/*     */     //   135: aaload
/*     */     //   136: astore 19
/*     */     //   138: iconst_3
/*     */     //   139: istore 17
/*     */     //   141: goto +279 -> 420
/*     */     //   144: aload_0
/*     */     //   145: iload 21
/*     */     //   147: aaload
/*     */     //   148: ldc 37
/*     */     //   150: invokevirtual 25	java/lang/String:equals	(Ljava/lang/Object;)Z
/*     */     //   153: ifeq +12 -> 165
/*     */     //   156: iconst_1
/*     */     //   157: istore 12
/*     */     //   159: iconst_3
/*     */     //   160: istore 17
/*     */     //   162: goto +258 -> 420
/*     */     //   165: aload_0
/*     */     //   166: iload 21
/*     */     //   168: aaload
/*     */     //   169: ldc 39
/*     */     //   171: invokevirtual 25	java/lang/String:equals	(Ljava/lang/Object;)Z
/*     */     //   174: ifeq +9 -> 183
/*     */     //   177: iconst_1
/*     */     //   178: istore 8
/*     */     //   180: goto +240 -> 420
/*     */     //   183: aload_0
/*     */     //   184: iload 21
/*     */     //   186: aaload
/*     */     //   187: ldc 41
/*     */     //   189: invokevirtual 25	java/lang/String:equals	(Ljava/lang/Object;)Z
/*     */     //   192: ifeq +12 -> 204
/*     */     //   195: iconst_1
/*     */     //   196: istore 9
/*     */     //   198: iconst_3
/*     */     //   199: istore 17
/*     */     //   201: goto +219 -> 420
/*     */     //   204: aload_0
/*     */     //   205: iload 21
/*     */     //   207: aaload
/*     */     //   208: ldc 43
/*     */     //   210: invokevirtual 25	java/lang/String:equals	(Ljava/lang/Object;)Z
/*     */     //   213: ifeq +9 -> 222
/*     */     //   216: iconst_1
/*     */     //   217: istore 6
/*     */     //   219: goto +201 -> 420
/*     */     //   222: aload_0
/*     */     //   223: iload 21
/*     */     //   225: aaload
/*     */     //   226: ldc 45
/*     */     //   228: invokevirtual 25	java/lang/String:equals	(Ljava/lang/Object;)Z
/*     */     //   231: ifeq +18 -> 249
/*     */     //   234: aload_0
/*     */     //   235: iinc 21 1
/*     */     //   238: iload 21
/*     */     //   240: aaload
/*     */     //   241: invokestatic 47	java/lang/Long:parseLong	(Ljava/lang/String;)J
/*     */     //   244: lstore 14
/*     */     //   246: goto +174 -> 420
/*     */     //   249: aload_0
/*     */     //   250: iload 21
/*     */     //   252: aaload
/*     */     //   253: ldc 53
/*     */     //   255: invokevirtual 25	java/lang/String:equals	(Ljava/lang/Object;)Z
/*     */     //   258: ifeq +12 -> 270
/*     */     //   261: iconst_1
/*     */     //   262: istore 4
/*     */     //   264: iconst_3
/*     */     //   265: istore 17
/*     */     //   267: goto +153 -> 420
/*     */     //   270: aload_0
/*     */     //   271: iload 21
/*     */     //   273: aaload
/*     */     //   274: ldc 55
/*     */     //   276: invokevirtual 25	java/lang/String:equals	(Ljava/lang/Object;)Z
/*     */     //   279: ifeq +9 -> 288
/*     */     //   282: iconst_1
/*     */     //   283: istore 13
/*     */     //   285: goto +135 -> 420
/*     */     //   288: aload_0
/*     */     //   289: iload 21
/*     */     //   291: aaload
/*     */     //   292: ldc 57
/*     */     //   294: invokevirtual 25	java/lang/String:equals	(Ljava/lang/Object;)Z
/*     */     //   297: ifeq +12 -> 309
/*     */     //   300: iconst_1
/*     */     //   301: istore 5
/*     */     //   303: iconst_3
/*     */     //   304: istore 17
/*     */     //   306: goto +114 -> 420
/*     */     //   309: aload_0
/*     */     //   310: iload 21
/*     */     //   312: aaload
/*     */     //   313: ldc 59
/*     */     //   315: invokevirtual 25	java/lang/String:equals	(Ljava/lang/Object;)Z
/*     */     //   318: ifeq +15 -> 333
/*     */     //   321: aload_0
/*     */     //   322: iinc 21 1
/*     */     //   325: iload 21
/*     */     //   327: aaload
/*     */     //   328: astore 18
/*     */     //   330: goto +90 -> 420
/*     */     //   333: aload_0
/*     */     //   334: iload 21
/*     */     //   336: aaload
/*     */     //   337: ldc 61
/*     */     //   339: invokevirtual 25	java/lang/String:equals	(Ljava/lang/Object;)Z
/*     */     //   342: ifeq +12 -> 354
/*     */     //   345: iconst_1
/*     */     //   346: istore 11
/*     */     //   348: iconst_3
/*     */     //   349: istore 17
/*     */     //   351: goto +69 -> 420
/*     */     //   354: aload_0
/*     */     //   355: iload 21
/*     */     //   357: aaload
/*     */     //   358: ldc 63
/*     */     //   360: invokevirtual 25	java/lang/String:equals	(Ljava/lang/Object;)Z
/*     */     //   363: ifeq +18 -> 381
/*     */     //   366: aload_0
/*     */     //   367: iinc 21 1
/*     */     //   370: iload 21
/*     */     //   372: aaload
/*     */     //   373: invokestatic 65	java/lang/Integer:parseInt	(Ljava/lang/String;)I
/*     */     //   376: istore 16
/*     */     //   378: goto +42 -> 420
/*     */     //   381: aload_0
/*     */     //   382: iload 21
/*     */     //   384: aaload
/*     */     //   385: ldc 71
/*     */     //   387: invokevirtual 25	java/lang/String:equals	(Ljava/lang/Object;)Z
/*     */     //   390: ifeq +15 -> 405
/*     */     //   393: aload_0
/*     */     //   394: iinc 21 1
/*     */     //   397: iload 21
/*     */     //   399: aaload
/*     */     //   400: astore 20
/*     */     //   402: goto +18 -> 420
/*     */     //   405: aload_0
/*     */     //   406: iload 21
/*     */     //   408: aaload
/*     */     //   409: ldc 73
/*     */     //   411: invokevirtual 25	java/lang/String:equals	(Ljava/lang/Object;)Z
/*     */     //   414: ifeq +16 -> 430
/*     */     //   417: iconst_1
/*     */     //   418: istore 10
/*     */     //   420: iinc 21 1
/*     */     //   423: iload 21
/*     */     //   425: aload_0
/*     */     //   426: arraylength
/*     */     //   427: if_icmplt -362 -> 65
/*     */     //   430: aload_0
/*     */     //   431: arraylength
/*     */     //   432: iload 21
/*     */     //   434: isub
/*     */     //   435: istore 22
/*     */     //   437: iload 22
/*     */     //   439: iload 17
/*     */     //   441: if_icmpge +15 -> 456
/*     */     //   444: getstatic 75	java/lang/System:err	Ljava/io/PrintStream;
/*     */     //   447: ldc 8
/*     */     //   449: invokevirtual 81	java/io/PrintStream:println	(Ljava/lang/String;)V
/*     */     //   452: iconst_1
/*     */     //   453: invokestatic 87	java/lang/System:exit	(I)V
/*     */     //   456: aload_0
/*     */     //   457: iload 21
/*     */     //   459: iinc 21 1
/*     */     //   462: aaload
/*     */     //   463: astore 23
/*     */     //   465: iconst_0
/*     */     //   466: istore 24
/*     */     //   468: aload 23
/*     */     //   470: ldc 91
/*     */     //   472: invokevirtual 93	java/lang/String:split	(Ljava/lang/String;)[Ljava/lang/String;
/*     */     //   475: astore 25
/*     */     //   477: aload 25
/*     */     //   479: arraylength
/*     */     //   480: iconst_2
/*     */     //   481: if_icmpne +18 -> 499
/*     */     //   484: aload 25
/*     */     //   486: iconst_0
/*     */     //   487: aaload
/*     */     //   488: astore 23
/*     */     //   490: aload 25
/*     */     //   492: iconst_1
/*     */     //   493: aaload
/*     */     //   494: invokestatic 65	java/lang/Integer:parseInt	(Ljava/lang/String;)I
/*     */     //   497: istore 24
/*     */     //   499: aload_0
/*     */     //   500: iload 21
/*     */     //   502: iinc 21 1
/*     */     //   505: aaload
/*     */     //   506: astore 26
/*     */     //   508: aload_0
/*     */     //   509: iload 21
/*     */     //   511: iinc 21 1
/*     */     //   514: aaload
/*     */     //   515: astore 27
/*     */     //   517: aconst_null
/*     */     //   518: astore 28
/*     */     //   520: aload_0
/*     */     //   521: arraylength
/*     */     //   522: iload 21
/*     */     //   524: isub
/*     */     //   525: ifle +12 -> 537
/*     */     //   528: aload_0
/*     */     //   529: iload 21
/*     */     //   531: iinc 21 1
/*     */     //   534: aaload
/*     */     //   535: astore 28
/*     */     //   537: aconst_null
/*     */     //   538: astore 29
/*     */     //   540: aload_0
/*     */     //   541: arraylength
/*     */     //   542: iload 21
/*     */     //   544: isub
/*     */     //   545: ifle +12 -> 557
/*     */     //   548: aload_0
/*     */     //   549: iload 21
/*     */     //   551: iinc 21 1
/*     */     //   554: aaload
/*     */     //   555: astore 29
/*     */     //   557: aload 18
/*     */     //   559: ifnonnull +15 -> 574
/*     */     //   562: new 97	org/apache/commons/net/ftp/FTPClient
/*     */     //   565: dup
/*     */     //   566: invokespecial 99	org/apache/commons/net/ftp/FTPClient:<init>	()V
/*     */     //   569: astore 30
/*     */     //   571: goto +161 -> 732
/*     */     //   574: aload 18
/*     */     //   576: ldc 100
/*     */     //   578: invokevirtual 25	java/lang/String:equals	(Ljava/lang/Object;)Z
/*     */     //   581: ifeq +16 -> 597
/*     */     //   584: new 102	org/apache/commons/net/ftp/FTPSClient
/*     */     //   587: dup
/*     */     //   588: iconst_1
/*     */     //   589: invokespecial 104	org/apache/commons/net/ftp/FTPSClient:<init>	(Z)V
/*     */     //   592: astore 31
/*     */     //   594: goto +76 -> 670
/*     */     //   597: aload 18
/*     */     //   599: ldc 107
/*     */     //   601: invokevirtual 25	java/lang/String:equals	(Ljava/lang/Object;)Z
/*     */     //   604: ifeq +16 -> 620
/*     */     //   607: new 102	org/apache/commons/net/ftp/FTPSClient
/*     */     //   610: dup
/*     */     //   611: iconst_0
/*     */     //   612: invokespecial 104	org/apache/commons/net/ftp/FTPSClient:<init>	(Z)V
/*     */     //   615: astore 31
/*     */     //   617: goto +53 -> 670
/*     */     //   620: aload 18
/*     */     //   622: ldc 109
/*     */     //   624: invokevirtual 93	java/lang/String:split	(Ljava/lang/String;)[Ljava/lang/String;
/*     */     //   627: astore 32
/*     */     //   629: aload 32
/*     */     //   631: arraylength
/*     */     //   632: iconst_1
/*     */     //   633: if_icmpne +17 -> 650
/*     */     //   636: new 102	org/apache/commons/net/ftp/FTPSClient
/*     */     //   639: dup
/*     */     //   640: aload 18
/*     */     //   642: invokespecial 111	org/apache/commons/net/ftp/FTPSClient:<init>	(Ljava/lang/String;)V
/*     */     //   645: astore 31
/*     */     //   647: goto +23 -> 670
/*     */     //   650: new 102	org/apache/commons/net/ftp/FTPSClient
/*     */     //   653: dup
/*     */     //   654: aload 32
/*     */     //   656: iconst_0
/*     */     //   657: aaload
/*     */     //   658: aload 32
/*     */     //   660: iconst_1
/*     */     //   661: aaload
/*     */     //   662: invokestatic 113	java/lang/Boolean:parseBoolean	(Ljava/lang/String;)Z
/*     */     //   665: invokespecial 119	org/apache/commons/net/ftp/FTPSClient:<init>	(Ljava/lang/String;Z)V
/*     */     //   668: astore 31
/*     */     //   670: aload 31
/*     */     //   672: astore 30
/*     */     //   674: ldc 122
/*     */     //   676: aload 20
/*     */     //   678: invokevirtual 25	java/lang/String:equals	(Ljava/lang/Object;)Z
/*     */     //   681: ifeq +14 -> 695
/*     */     //   684: aload 31
/*     */     //   686: invokestatic 124	org/apache/commons/net/util/TrustManagerUtils:getAcceptAllTrustManager	()Ljavax/net/ssl/X509TrustManager;
/*     */     //   689: invokevirtual 130	org/apache/commons/net/ftp/FTPSClient:setTrustManager	(Ljavax/net/ssl/TrustManager;)V
/*     */     //   692: goto +40 -> 732
/*     */     //   695: ldc -122
/*     */     //   697: aload 20
/*     */     //   699: invokevirtual 25	java/lang/String:equals	(Ljava/lang/Object;)Z
/*     */     //   702: ifeq +14 -> 716
/*     */     //   705: aload 31
/*     */     //   707: invokestatic 136	org/apache/commons/net/util/TrustManagerUtils:getValidateServerCertificateTrustManager	()Ljavax/net/ssl/X509TrustManager;
/*     */     //   710: invokevirtual 130	org/apache/commons/net/ftp/FTPSClient:setTrustManager	(Ljavax/net/ssl/TrustManager;)V
/*     */     //   713: goto +19 -> 732
/*     */     //   716: ldc -117
/*     */     //   718: aload 20
/*     */     //   720: invokevirtual 25	java/lang/String:equals	(Ljava/lang/Object;)Z
/*     */     //   723: ifeq +9 -> 732
/*     */     //   726: aload 31
/*     */     //   728: aconst_null
/*     */     //   729: invokevirtual 130	org/apache/commons/net/ftp/FTPSClient:setTrustManager	(Ljavax/net/ssl/TrustManager;)V
/*     */     //   732: iload 10
/*     */     //   734: ifeq +11 -> 745
/*     */     //   737: aload 30
/*     */     //   739: invokestatic 141	examples/ftp/FTPClientExample:createListener	()Lorg/apache/commons/net/io/CopyStreamListener;
/*     */     //   742: invokevirtual 145	org/apache/commons/net/ftp/FTPClient:setCopyStreamListener	(Lorg/apache/commons/net/io/CopyStreamListener;)V
/*     */     //   745: lload 14
/*     */     //   747: lconst_0
/*     */     //   748: lcmp
/*     */     //   749: iflt +10 -> 759
/*     */     //   752: aload 30
/*     */     //   754: lload 14
/*     */     //   756: invokevirtual 149	org/apache/commons/net/ftp/FTPClient:setControlKeepAliveTimeout	(J)V
/*     */     //   759: iload 16
/*     */     //   761: iflt +10 -> 771
/*     */     //   764: aload 30
/*     */     //   766: iload 16
/*     */     //   768: invokevirtual 153	org/apache/commons/net/ftp/FTPClient:setControlKeepAliveReplyTimeout	(I)V
/*     */     //   771: aload 30
/*     */     //   773: iload 6
/*     */     //   775: invokevirtual 156	org/apache/commons/net/ftp/FTPClient:setListHiddenFiles	(Z)V
/*     */     //   778: aload 30
/*     */     //   780: new 159	org/apache/commons/net/PrintCommandListener
/*     */     //   783: dup
/*     */     //   784: new 161	java/io/PrintWriter
/*     */     //   787: dup
/*     */     //   788: getstatic 163	java/lang/System:out	Ljava/io/PrintStream;
/*     */     //   791: invokespecial 166	java/io/PrintWriter:<init>	(Ljava/io/OutputStream;)V
/*     */     //   794: iconst_1
/*     */     //   795: invokespecial 169	org/apache/commons/net/PrintCommandListener:<init>	(Ljava/io/PrintWriter;Z)V
/*     */     //   798: invokevirtual 172	org/apache/commons/net/ftp/FTPClient:addProtocolCommandListener	(Lorg/apache/commons/net/ProtocolCommandListener;)V
/*     */     //   801: iload 24
/*     */     //   803: ifle +15 -> 818
/*     */     //   806: aload 30
/*     */     //   808: aload 23
/*     */     //   810: iload 24
/*     */     //   812: invokevirtual 176	org/apache/commons/net/ftp/FTPClient:connect	(Ljava/lang/String;I)V
/*     */     //   815: goto +10 -> 825
/*     */     //   818: aload 30
/*     */     //   820: aload 23
/*     */     //   822: invokevirtual 180	org/apache/commons/net/ftp/FTPClient:connect	(Ljava/lang/String;)V
/*     */     //   825: getstatic 163	java/lang/System:out	Ljava/io/PrintStream;
/*     */     //   828: new 182	java/lang/StringBuilder
/*     */     //   831: dup
/*     */     //   832: ldc -72
/*     */     //   834: invokespecial 186	java/lang/StringBuilder:<init>	(Ljava/lang/String;)V
/*     */     //   837: aload 23
/*     */     //   839: invokevirtual 187	java/lang/StringBuilder:append	(Ljava/lang/String;)Ljava/lang/StringBuilder;
/*     */     //   842: ldc -65
/*     */     //   844: invokevirtual 187	java/lang/StringBuilder:append	(Ljava/lang/String;)Ljava/lang/StringBuilder;
/*     */     //   847: aload 30
/*     */     //   849: invokevirtual 193	org/apache/commons/net/ftp/FTPClient:getRemotePort	()I
/*     */     //   852: invokevirtual 197	java/lang/StringBuilder:append	(I)Ljava/lang/StringBuilder;
/*     */     //   855: invokevirtual 200	java/lang/StringBuilder:toString	()Ljava/lang/String;
/*     */     //   858: invokevirtual 81	java/io/PrintStream:println	(Ljava/lang/String;)V
/*     */     //   861: aload 30
/*     */     //   863: invokevirtual 204	org/apache/commons/net/ftp/FTPClient:getReplyCode	()I
/*     */     //   866: istore 31
/*     */     //   868: iload 31
/*     */     //   870: invokestatic 207	org/apache/commons/net/ftp/FTPReply:isPositiveCompletion	(I)Z
/*     */     //   873: ifne +59 -> 932
/*     */     //   876: aload 30
/*     */     //   878: invokevirtual 213	org/apache/commons/net/ftp/FTPClient:disconnect	()V
/*     */     //   881: getstatic 75	java/lang/System:err	Ljava/io/PrintStream;
/*     */     //   884: ldc -40
/*     */     //   886: invokevirtual 81	java/io/PrintStream:println	(Ljava/lang/String;)V
/*     */     //   889: iconst_1
/*     */     //   890: invokestatic 87	java/lang/System:exit	(I)V
/*     */     //   893: goto +39 -> 932
/*     */     //   896: astore 31
/*     */     //   898: aload 30
/*     */     //   900: invokevirtual 218	org/apache/commons/net/ftp/FTPClient:isConnected	()Z
/*     */     //   903: ifeq +12 -> 915
/*     */     //   906: aload 30
/*     */     //   908: invokevirtual 213	org/apache/commons/net/ftp/FTPClient:disconnect	()V
/*     */     //   911: goto +4 -> 915
/*     */     //   914: pop
/*     */     //   915: getstatic 75	java/lang/System:err	Ljava/io/PrintStream;
/*     */     //   918: ldc -34
/*     */     //   920: invokevirtual 81	java/io/PrintStream:println	(Ljava/lang/String;)V
/*     */     //   923: aload 31
/*     */     //   925: invokevirtual 224	java/io/IOException:printStackTrace	()V
/*     */     //   928: iconst_1
/*     */     //   929: invokestatic 87	java/lang/System:exit	(I)V
/*     */     //   932: aload 30
/*     */     //   934: aload 26
/*     */     //   936: aload 27
/*     */     //   938: invokevirtual 229	org/apache/commons/net/ftp/FTPClient:login	(Ljava/lang/String;Ljava/lang/String;)Z
/*     */     //   941: ifne +31 -> 972
/*     */     //   944: aload 30
/*     */     //   946: invokevirtual 233	org/apache/commons/net/ftp/FTPClient:logout	()Z
/*     */     //   949: pop
/*     */     //   950: iconst_1
/*     */     //   951: istore_3
/*     */     //   952: aload 30
/*     */     //   954: invokevirtual 218	org/apache/commons/net/ftp/FTPClient:isConnected	()Z
/*     */     //   957: ifeq +867 -> 1824
/*     */     //   960: aload 30
/*     */     //   962: invokevirtual 213	org/apache/commons/net/ftp/FTPClient:disconnect	()V
/*     */     //   965: goto +859 -> 1824
/*     */     //   968: pop
/*     */     //   969: goto +855 -> 1824
/*     */     //   972: getstatic 163	java/lang/System:out	Ljava/io/PrintStream;
/*     */     //   975: new 182	java/lang/StringBuilder
/*     */     //   978: dup
/*     */     //   979: ldc -20
/*     */     //   981: invokespecial 186	java/lang/StringBuilder:<init>	(Ljava/lang/String;)V
/*     */     //   984: aload 30
/*     */     //   986: invokevirtual 238	org/apache/commons/net/ftp/FTPClient:getSystemType	()Ljava/lang/String;
/*     */     //   989: invokevirtual 187	java/lang/StringBuilder:append	(Ljava/lang/String;)Ljava/lang/StringBuilder;
/*     */     //   992: invokevirtual 200	java/lang/StringBuilder:toString	()Ljava/lang/String;
/*     */     //   995: invokevirtual 81	java/io/PrintStream:println	(Ljava/lang/String;)V
/*     */     //   998: iload_2
/*     */     //   999: ifeq +10 -> 1009
/*     */     //   1002: aload 30
/*     */     //   1004: iconst_2
/*     */     //   1005: invokevirtual 241	org/apache/commons/net/ftp/FTPClient:setFileType	(I)Z
/*     */     //   1008: pop
/*     */     //   1009: iload 7
/*     */     //   1011: ifeq +11 -> 1022
/*     */     //   1014: aload 30
/*     */     //   1016: invokevirtual 244	org/apache/commons/net/ftp/FTPClient:enterLocalActiveMode	()V
/*     */     //   1019: goto +8 -> 1027
/*     */     //   1022: aload 30
/*     */     //   1024: invokevirtual 247	org/apache/commons/net/ftp/FTPClient:enterLocalPassiveMode	()V
/*     */     //   1027: aload 30
/*     */     //   1029: iload 8
/*     */     //   1031: invokevirtual 250	org/apache/commons/net/ftp/FTPClient:setUseEPSVwithIPv4	(Z)V
/*     */     //   1034: iload_1
/*     */     //   1035: ifeq +32 -> 1067
/*     */     //   1038: new 253	java/io/FileInputStream
/*     */     //   1041: dup
/*     */     //   1042: aload 29
/*     */     //   1044: invokespecial 255	java/io/FileInputStream:<init>	(Ljava/lang/String;)V
/*     */     //   1047: astore 31
/*     */     //   1049: aload 30
/*     */     //   1051: aload 28
/*     */     //   1053: aload 31
/*     */     //   1055: invokevirtual 256	org/apache/commons/net/ftp/FTPClient:storeFile	(Ljava/lang/String;Ljava/io/InputStream;)Z
/*     */     //   1058: pop
/*     */     //   1059: aload 31
/*     */     //   1061: invokevirtual 260	java/io/InputStream:close	()V
/*     */     //   1064: goto +639 -> 1703
/*     */     //   1067: iload 4
/*     */     //   1069: ifeq +91 -> 1160
/*     */     //   1072: iload 13
/*     */     //   1074: ifeq +25 -> 1099
/*     */     //   1077: new 265	org/apache/commons/net/ftp/FTPClientConfig
/*     */     //   1080: dup
/*     */     //   1081: invokespecial 267	org/apache/commons/net/ftp/FTPClientConfig:<init>	()V
/*     */     //   1084: astore 31
/*     */     //   1086: aload 31
/*     */     //   1088: iconst_1
/*     */     //   1089: invokevirtual 268	org/apache/commons/net/ftp/FTPClientConfig:setLenientFutureDates	(Z)V
/*     */     //   1092: aload 30
/*     */     //   1094: aload 31
/*     */     //   1096: invokevirtual 271	org/apache/commons/net/ftp/FTPClient:configure	(Lorg/apache/commons/net/ftp/FTPClientConfig;)V
/*     */     //   1099: aload 30
/*     */     //   1101: aload 28
/*     */     //   1103: invokevirtual 275	org/apache/commons/net/ftp/FTPClient:listFiles	(Ljava/lang/String;)[Lorg/apache/commons/net/ftp/FTPFile;
/*     */     //   1106: dup
/*     */     //   1107: astore 34
/*     */     //   1109: arraylength
/*     */     //   1110: istore 33
/*     */     //   1112: iconst_0
/*     */     //   1113: istore 32
/*     */     //   1115: goto +35 -> 1150
/*     */     //   1118: aload 34
/*     */     //   1120: iload 32
/*     */     //   1122: aaload
/*     */     //   1123: astore 31
/*     */     //   1125: getstatic 163	java/lang/System:out	Ljava/io/PrintStream;
/*     */     //   1128: aload 31
/*     */     //   1130: invokevirtual 279	org/apache/commons/net/ftp/FTPFile:getRawListing	()Ljava/lang/String;
/*     */     //   1133: invokevirtual 81	java/io/PrintStream:println	(Ljava/lang/String;)V
/*     */     //   1136: getstatic 163	java/lang/System:out	Ljava/io/PrintStream;
/*     */     //   1139: aload 31
/*     */     //   1141: invokevirtual 284	org/apache/commons/net/ftp/FTPFile:toFormattedString	()Ljava/lang/String;
/*     */     //   1144: invokevirtual 81	java/io/PrintStream:println	(Ljava/lang/String;)V
/*     */     //   1147: iinc 32 1
/*     */     //   1150: iload 32
/*     */     //   1152: iload 33
/*     */     //   1154: if_icmplt -36 -> 1118
/*     */     //   1157: goto +546 -> 1703
/*     */     //   1160: iload 12
/*     */     //   1162: ifeq +64 -> 1226
/*     */     //   1165: aload 30
/*     */     //   1167: aload 28
/*     */     //   1169: invokevirtual 287	org/apache/commons/net/ftp/FTPClient:mlistDir	(Ljava/lang/String;)[Lorg/apache/commons/net/ftp/FTPFile;
/*     */     //   1172: dup
/*     */     //   1173: astore 34
/*     */     //   1175: arraylength
/*     */     //   1176: istore 33
/*     */     //   1178: iconst_0
/*     */     //   1179: istore 32
/*     */     //   1181: goto +35 -> 1216
/*     */     //   1184: aload 34
/*     */     //   1186: iload 32
/*     */     //   1188: aaload
/*     */     //   1189: astore 31
/*     */     //   1191: getstatic 163	java/lang/System:out	Ljava/io/PrintStream;
/*     */     //   1194: aload 31
/*     */     //   1196: invokevirtual 279	org/apache/commons/net/ftp/FTPFile:getRawListing	()Ljava/lang/String;
/*     */     //   1199: invokevirtual 81	java/io/PrintStream:println	(Ljava/lang/String;)V
/*     */     //   1202: getstatic 163	java/lang/System:out	Ljava/io/PrintStream;
/*     */     //   1205: aload 31
/*     */     //   1207: invokevirtual 284	org/apache/commons/net/ftp/FTPFile:toFormattedString	()Ljava/lang/String;
/*     */     //   1210: invokevirtual 81	java/io/PrintStream:println	(Ljava/lang/String;)V
/*     */     //   1213: iinc 32 1
/*     */     //   1216: iload 32
/*     */     //   1218: iload 33
/*     */     //   1220: if_icmplt -36 -> 1184
/*     */     //   1223: goto +480 -> 1703
/*     */     //   1226: iload 11
/*     */     //   1228: ifeq +31 -> 1259
/*     */     //   1231: aload 30
/*     */     //   1233: aload 28
/*     */     //   1235: invokevirtual 290	org/apache/commons/net/ftp/FTPClient:mlistFile	(Ljava/lang/String;)Lorg/apache/commons/net/ftp/FTPFile;
/*     */     //   1238: astore 31
/*     */     //   1240: aload 31
/*     */     //   1242: ifnull +461 -> 1703
/*     */     //   1245: getstatic 163	java/lang/System:out	Ljava/io/PrintStream;
/*     */     //   1248: aload 31
/*     */     //   1250: invokevirtual 284	org/apache/commons/net/ftp/FTPFile:toFormattedString	()Ljava/lang/String;
/*     */     //   1253: invokevirtual 81	java/io/PrintStream:println	(Ljava/lang/String;)V
/*     */     //   1256: goto +447 -> 1703
/*     */     //   1259: iload 5
/*     */     //   1261: ifeq +50 -> 1311
/*     */     //   1264: aload 30
/*     */     //   1266: aload 28
/*     */     //   1268: invokevirtual 294	org/apache/commons/net/ftp/FTPClient:listNames	(Ljava/lang/String;)[Ljava/lang/String;
/*     */     //   1271: dup
/*     */     //   1272: astore 34
/*     */     //   1274: arraylength
/*     */     //   1275: istore 33
/*     */     //   1277: iconst_0
/*     */     //   1278: istore 32
/*     */     //   1280: goto +21 -> 1301
/*     */     //   1283: aload 34
/*     */     //   1285: iload 32
/*     */     //   1287: aaload
/*     */     //   1288: astore 31
/*     */     //   1290: getstatic 163	java/lang/System:out	Ljava/io/PrintStream;
/*     */     //   1293: aload 31
/*     */     //   1295: invokevirtual 81	java/io/PrintStream:println	(Ljava/lang/String;)V
/*     */     //   1298: iinc 32 1
/*     */     //   1301: iload 32
/*     */     //   1303: iload 33
/*     */     //   1305: if_icmplt -22 -> 1283
/*     */     //   1308: goto +395 -> 1703
/*     */     //   1311: iload 9
/*     */     //   1313: ifeq +317 -> 1630
/*     */     //   1316: aload 28
/*     */     //   1318: ifnull +274 -> 1592
/*     */     //   1321: aload 30
/*     */     //   1323: aload 28
/*     */     //   1325: invokevirtual 297	org/apache/commons/net/ftp/FTPClient:hasFeature	(Ljava/lang/String;)Z
/*     */     //   1328: ifeq +30 -> 1358
/*     */     //   1331: getstatic 163	java/lang/System:out	Ljava/io/PrintStream;
/*     */     //   1334: new 182	java/lang/StringBuilder
/*     */     //   1337: dup
/*     */     //   1338: ldc_w 300
/*     */     //   1341: invokespecial 186	java/lang/StringBuilder:<init>	(Ljava/lang/String;)V
/*     */     //   1344: aload 28
/*     */     //   1346: invokevirtual 187	java/lang/StringBuilder:append	(Ljava/lang/String;)Ljava/lang/StringBuilder;
/*     */     //   1349: invokevirtual 200	java/lang/StringBuilder:toString	()Ljava/lang/String;
/*     */     //   1352: invokevirtual 81	java/io/PrintStream:println	(Ljava/lang/String;)V
/*     */     //   1355: goto +74 -> 1429
/*     */     //   1358: aload 30
/*     */     //   1360: invokevirtual 204	org/apache/commons/net/ftp/FTPClient:getReplyCode	()I
/*     */     //   1363: invokestatic 207	org/apache/commons/net/ftp/FTPReply:isPositiveCompletion	(I)Z
/*     */     //   1366: ifeq +36 -> 1402
/*     */     //   1369: getstatic 163	java/lang/System:out	Ljava/io/PrintStream;
/*     */     //   1372: new 182	java/lang/StringBuilder
/*     */     //   1375: dup
/*     */     //   1376: ldc_w 302
/*     */     //   1379: invokespecial 186	java/lang/StringBuilder:<init>	(Ljava/lang/String;)V
/*     */     //   1382: aload 28
/*     */     //   1384: invokevirtual 187	java/lang/StringBuilder:append	(Ljava/lang/String;)Ljava/lang/StringBuilder;
/*     */     //   1387: ldc_w 304
/*     */     //   1390: invokevirtual 187	java/lang/StringBuilder:append	(Ljava/lang/String;)Ljava/lang/StringBuilder;
/*     */     //   1393: invokevirtual 200	java/lang/StringBuilder:toString	()Ljava/lang/String;
/*     */     //   1396: invokevirtual 81	java/io/PrintStream:println	(Ljava/lang/String;)V
/*     */     //   1399: goto +30 -> 1429
/*     */     //   1402: getstatic 163	java/lang/System:out	Ljava/io/PrintStream;
/*     */     //   1405: new 182	java/lang/StringBuilder
/*     */     //   1408: dup
/*     */     //   1409: ldc_w 306
/*     */     //   1412: invokespecial 186	java/lang/StringBuilder:<init>	(Ljava/lang/String;)V
/*     */     //   1415: aload 30
/*     */     //   1417: invokevirtual 308	org/apache/commons/net/ftp/FTPClient:getReplyString	()Ljava/lang/String;
/*     */     //   1420: invokevirtual 187	java/lang/StringBuilder:append	(Ljava/lang/String;)Ljava/lang/StringBuilder;
/*     */     //   1423: invokevirtual 200	java/lang/StringBuilder:toString	()Ljava/lang/String;
/*     */     //   1426: invokevirtual 81	java/io/PrintStream:println	(Ljava/lang/String;)V
/*     */     //   1429: aload 30
/*     */     //   1431: aload 28
/*     */     //   1433: invokevirtual 311	org/apache/commons/net/ftp/FTPClient:featureValues	(Ljava/lang/String;)[Ljava/lang/String;
/*     */     //   1436: astore 31
/*     */     //   1438: aload 31
/*     */     //   1440: ifnull +78 -> 1518
/*     */     //   1443: aload 31
/*     */     //   1445: dup
/*     */     //   1446: astore 35
/*     */     //   1448: arraylength
/*     */     //   1449: istore 34
/*     */     //   1451: iconst_0
/*     */     //   1452: istore 33
/*     */     //   1454: goto +54 -> 1508
/*     */     //   1457: aload 35
/*     */     //   1459: iload 33
/*     */     //   1461: aaload
/*     */     //   1462: astore 32
/*     */     //   1464: getstatic 163	java/lang/System:out	Ljava/io/PrintStream;
/*     */     //   1467: new 182	java/lang/StringBuilder
/*     */     //   1470: dup
/*     */     //   1471: ldc_w 302
/*     */     //   1474: invokespecial 186	java/lang/StringBuilder:<init>	(Ljava/lang/String;)V
/*     */     //   1477: aload 28
/*     */     //   1479: invokevirtual 187	java/lang/StringBuilder:append	(Ljava/lang/String;)Ljava/lang/StringBuilder;
/*     */     //   1482: ldc_w 314
/*     */     //   1485: invokevirtual 187	java/lang/StringBuilder:append	(Ljava/lang/String;)Ljava/lang/StringBuilder;
/*     */     //   1488: aload 32
/*     */     //   1490: invokevirtual 187	java/lang/StringBuilder:append	(Ljava/lang/String;)Ljava/lang/StringBuilder;
/*     */     //   1493: ldc_w 316
/*     */     //   1496: invokevirtual 187	java/lang/StringBuilder:append	(Ljava/lang/String;)Ljava/lang/StringBuilder;
/*     */     //   1499: invokevirtual 200	java/lang/StringBuilder:toString	()Ljava/lang/String;
/*     */     //   1502: invokevirtual 81	java/io/PrintStream:println	(Ljava/lang/String;)V
/*     */     //   1505: iinc 33 1
/*     */     //   1508: iload 33
/*     */     //   1510: iload 34
/*     */     //   1512: if_icmplt -55 -> 1457
/*     */     //   1515: goto +188 -> 1703
/*     */     //   1518: aload 30
/*     */     //   1520: invokevirtual 204	org/apache/commons/net/ftp/FTPClient:getReplyCode	()I
/*     */     //   1523: invokestatic 207	org/apache/commons/net/ftp/FTPReply:isPositiveCompletion	(I)Z
/*     */     //   1526: ifeq +36 -> 1562
/*     */     //   1529: getstatic 163	java/lang/System:out	Ljava/io/PrintStream;
/*     */     //   1532: new 182	java/lang/StringBuilder
/*     */     //   1535: dup
/*     */     //   1536: ldc_w 302
/*     */     //   1539: invokespecial 186	java/lang/StringBuilder:<init>	(Ljava/lang/String;)V
/*     */     //   1542: aload 28
/*     */     //   1544: invokevirtual 187	java/lang/StringBuilder:append	(Ljava/lang/String;)Ljava/lang/StringBuilder;
/*     */     //   1547: ldc_w 318
/*     */     //   1550: invokevirtual 187	java/lang/StringBuilder:append	(Ljava/lang/String;)Ljava/lang/StringBuilder;
/*     */     //   1553: invokevirtual 200	java/lang/StringBuilder:toString	()Ljava/lang/String;
/*     */     //   1556: invokevirtual 81	java/io/PrintStream:println	(Ljava/lang/String;)V
/*     */     //   1559: goto +144 -> 1703
/*     */     //   1562: getstatic 163	java/lang/System:out	Ljava/io/PrintStream;
/*     */     //   1565: new 182	java/lang/StringBuilder
/*     */     //   1568: dup
/*     */     //   1569: ldc_w 306
/*     */     //   1572: invokespecial 186	java/lang/StringBuilder:<init>	(Ljava/lang/String;)V
/*     */     //   1575: aload 30
/*     */     //   1577: invokevirtual 308	org/apache/commons/net/ftp/FTPClient:getReplyString	()Ljava/lang/String;
/*     */     //   1580: invokevirtual 187	java/lang/StringBuilder:append	(Ljava/lang/String;)Ljava/lang/StringBuilder;
/*     */     //   1583: invokevirtual 200	java/lang/StringBuilder:toString	()Ljava/lang/String;
/*     */     //   1586: invokevirtual 81	java/io/PrintStream:println	(Ljava/lang/String;)V
/*     */     //   1589: goto +114 -> 1703
/*     */     //   1592: aload 30
/*     */     //   1594: invokevirtual 320	org/apache/commons/net/ftp/FTPClient:features	()Z
/*     */     //   1597: ifne +106 -> 1703
/*     */     //   1600: getstatic 163	java/lang/System:out	Ljava/io/PrintStream;
/*     */     //   1603: new 182	java/lang/StringBuilder
/*     */     //   1606: dup
/*     */     //   1607: ldc_w 323
/*     */     //   1610: invokespecial 186	java/lang/StringBuilder:<init>	(Ljava/lang/String;)V
/*     */     //   1613: aload 30
/*     */     //   1615: invokevirtual 308	org/apache/commons/net/ftp/FTPClient:getReplyString	()Ljava/lang/String;
/*     */     //   1618: invokevirtual 187	java/lang/StringBuilder:append	(Ljava/lang/String;)Ljava/lang/StringBuilder;
/*     */     //   1621: invokevirtual 200	java/lang/StringBuilder:toString	()Ljava/lang/String;
/*     */     //   1624: invokevirtual 81	java/io/PrintStream:println	(Ljava/lang/String;)V
/*     */     //   1627: goto +76 -> 1703
/*     */     //   1630: aload 19
/*     */     //   1632: ifnull +45 -> 1677
/*     */     //   1635: aload 30
/*     */     //   1637: aload 19
/*     */     //   1639: aload 28
/*     */     //   1641: invokevirtual 325	org/apache/commons/net/ftp/FTPClient:doCommand	(Ljava/lang/String;Ljava/lang/String;)Z
/*     */     //   1644: ifne +59 -> 1703
/*     */     //   1647: getstatic 163	java/lang/System:out	Ljava/io/PrintStream;
/*     */     //   1650: new 182	java/lang/StringBuilder
/*     */     //   1653: dup
/*     */     //   1654: ldc_w 323
/*     */     //   1657: invokespecial 186	java/lang/StringBuilder:<init>	(Ljava/lang/String;)V
/*     */     //   1660: aload 30
/*     */     //   1662: invokevirtual 308	org/apache/commons/net/ftp/FTPClient:getReplyString	()Ljava/lang/String;
/*     */     //   1665: invokevirtual 187	java/lang/StringBuilder:append	(Ljava/lang/String;)Ljava/lang/StringBuilder;
/*     */     //   1668: invokevirtual 200	java/lang/StringBuilder:toString	()Ljava/lang/String;
/*     */     //   1671: invokevirtual 81	java/io/PrintStream:println	(Ljava/lang/String;)V
/*     */     //   1674: goto +29 -> 1703
/*     */     //   1677: new 328	java/io/FileOutputStream
/*     */     //   1680: dup
/*     */     //   1681: aload 29
/*     */     //   1683: invokespecial 330	java/io/FileOutputStream:<init>	(Ljava/lang/String;)V
/*     */     //   1686: astore 31
/*     */     //   1688: aload 30
/*     */     //   1690: aload 28
/*     */     //   1692: aload 31
/*     */     //   1694: invokevirtual 331	org/apache/commons/net/ftp/FTPClient:retrieveFile	(Ljava/lang/String;Ljava/io/OutputStream;)Z
/*     */     //   1697: pop
/*     */     //   1698: aload 31
/*     */     //   1700: invokevirtual 335	java/io/OutputStream:close	()V
/*     */     //   1703: aload 30
/*     */     //   1705: invokevirtual 338	org/apache/commons/net/ftp/FTPClient:noop	()I
/*     */     //   1708: pop
/*     */     //   1709: aload 30
/*     */     //   1711: invokevirtual 233	org/apache/commons/net/ftp/FTPClient:logout	()Z
/*     */     //   1714: pop
/*     */     //   1715: goto +92 -> 1807
/*     */     //   1718: astore 31
/*     */     //   1720: iconst_1
/*     */     //   1721: istore_3
/*     */     //   1722: getstatic 75	java/lang/System:err	Ljava/io/PrintStream;
/*     */     //   1725: ldc_w 341
/*     */     //   1728: invokevirtual 81	java/io/PrintStream:println	(Ljava/lang/String;)V
/*     */     //   1731: aload 31
/*     */     //   1733: invokevirtual 343	org/apache/commons/net/ftp/FTPConnectionClosedException:printStackTrace	()V
/*     */     //   1736: aload 30
/*     */     //   1738: invokevirtual 218	org/apache/commons/net/ftp/FTPClient:isConnected	()Z
/*     */     //   1741: ifeq +83 -> 1824
/*     */     //   1744: aload 30
/*     */     //   1746: invokevirtual 213	org/apache/commons/net/ftp/FTPClient:disconnect	()V
/*     */     //   1749: goto +75 -> 1824
/*     */     //   1752: pop
/*     */     //   1753: goto +71 -> 1824
/*     */     //   1756: astore 31
/*     */     //   1758: iconst_1
/*     */     //   1759: istore_3
/*     */     //   1760: aload 31
/*     */     //   1762: invokevirtual 224	java/io/IOException:printStackTrace	()V
/*     */     //   1765: aload 30
/*     */     //   1767: invokevirtual 218	org/apache/commons/net/ftp/FTPClient:isConnected	()Z
/*     */     //   1770: ifeq +54 -> 1824
/*     */     //   1773: aload 30
/*     */     //   1775: invokevirtual 213	org/apache/commons/net/ftp/FTPClient:disconnect	()V
/*     */     //   1778: goto +46 -> 1824
/*     */     //   1781: pop
/*     */     //   1782: goto +42 -> 1824
/*     */     //   1785: astore 36
/*     */     //   1787: aload 30
/*     */     //   1789: invokevirtual 218	org/apache/commons/net/ftp/FTPClient:isConnected	()Z
/*     */     //   1792: ifeq +12 -> 1804
/*     */     //   1795: aload 30
/*     */     //   1797: invokevirtual 213	org/apache/commons/net/ftp/FTPClient:disconnect	()V
/*     */     //   1800: goto +4 -> 1804
/*     */     //   1803: pop
/*     */     //   1804: aload 36
/*     */     //   1806: athrow
/*     */     //   1807: aload 30
/*     */     //   1809: invokevirtual 218	org/apache/commons/net/ftp/FTPClient:isConnected	()Z
/*     */     //   1812: ifeq +12 -> 1824
/*     */     //   1815: aload 30
/*     */     //   1817: invokevirtual 213	org/apache/commons/net/ftp/FTPClient:disconnect	()V
/*     */     //   1820: goto +4 -> 1824
/*     */     //   1823: pop
/*     */     //   1824: iload_3
/*     */     //   1825: ifeq +7 -> 1832
/*     */     //   1828: iconst_1
/*     */     //   1829: goto +4 -> 1833
/*     */     //   1832: iconst_0
/*     */     //   1833: invokestatic 87	java/lang/System:exit	(I)V
/*     */     //   1836: return
/*     */     // Line number table:
/*     */     //   Java source line #75	-> byte code offset #0
/*     */     //   Java source line #76	-> byte code offset #15
/*     */     //   Java source line #77	-> byte code offset #27
/*     */     //   Java source line #78	-> byte code offset #33
/*     */     //   Java source line #79	-> byte code offset #36
/*     */     //   Java source line #80	-> byte code offset #41
/*     */     //   Java source line #81	-> byte code offset #44
/*     */     //   Java source line #82	-> byte code offset #47
/*     */     //   Java source line #83	-> byte code offset #50
/*     */     //   Java source line #84	-> byte code offset #53
/*     */     //   Java source line #86	-> byte code offset #56
/*     */     //   Java source line #87	-> byte code offset #59
/*     */     //   Java source line #89	-> byte code offset #65
/*     */     //   Java source line #90	-> byte code offset #77
/*     */     //   Java source line #92	-> byte code offset #82
/*     */     //   Java source line #93	-> byte code offset #94
/*     */     //   Java source line #95	-> byte code offset #100
/*     */     //   Java source line #96	-> byte code offset #112
/*     */     //   Java source line #98	-> byte code offset #117
/*     */     //   Java source line #99	-> byte code offset #129
/*     */     //   Java source line #100	-> byte code offset #138
/*     */     //   Java source line #102	-> byte code offset #144
/*     */     //   Java source line #103	-> byte code offset #156
/*     */     //   Java source line #104	-> byte code offset #159
/*     */     //   Java source line #106	-> byte code offset #165
/*     */     //   Java source line #107	-> byte code offset #177
/*     */     //   Java source line #109	-> byte code offset #183
/*     */     //   Java source line #110	-> byte code offset #195
/*     */     //   Java source line #111	-> byte code offset #198
/*     */     //   Java source line #113	-> byte code offset #204
/*     */     //   Java source line #114	-> byte code offset #216
/*     */     //   Java source line #116	-> byte code offset #222
/*     */     //   Java source line #117	-> byte code offset #234
/*     */     //   Java source line #119	-> byte code offset #249
/*     */     //   Java source line #120	-> byte code offset #261
/*     */     //   Java source line #121	-> byte code offset #264
/*     */     //   Java source line #123	-> byte code offset #270
/*     */     //   Java source line #124	-> byte code offset #282
/*     */     //   Java source line #126	-> byte code offset #288
/*     */     //   Java source line #127	-> byte code offset #300
/*     */     //   Java source line #128	-> byte code offset #303
/*     */     //   Java source line #130	-> byte code offset #309
/*     */     //   Java source line #131	-> byte code offset #321
/*     */     //   Java source line #133	-> byte code offset #333
/*     */     //   Java source line #134	-> byte code offset #345
/*     */     //   Java source line #135	-> byte code offset #348
/*     */     //   Java source line #137	-> byte code offset #354
/*     */     //   Java source line #138	-> byte code offset #366
/*     */     //   Java source line #140	-> byte code offset #381
/*     */     //   Java source line #141	-> byte code offset #393
/*     */     //   Java source line #143	-> byte code offset #405
/*     */     //   Java source line #144	-> byte code offset #417
/*     */     //   Java source line #87	-> byte code offset #420
/*     */     //   Java source line #151	-> byte code offset #430
/*     */     //   Java source line #152	-> byte code offset #437
/*     */     //   Java source line #154	-> byte code offset #444
/*     */     //   Java source line #155	-> byte code offset #452
/*     */     //   Java source line #158	-> byte code offset #456
/*     */     //   Java source line #159	-> byte code offset #465
/*     */     //   Java source line #160	-> byte code offset #468
/*     */     //   Java source line #161	-> byte code offset #477
/*     */     //   Java source line #162	-> byte code offset #484
/*     */     //   Java source line #163	-> byte code offset #490
/*     */     //   Java source line #165	-> byte code offset #499
/*     */     //   Java source line #166	-> byte code offset #508
/*     */     //   Java source line #168	-> byte code offset #517
/*     */     //   Java source line #169	-> byte code offset #520
/*     */     //   Java source line #170	-> byte code offset #528
/*     */     //   Java source line #173	-> byte code offset #537
/*     */     //   Java source line #174	-> byte code offset #540
/*     */     //   Java source line #175	-> byte code offset #548
/*     */     //   Java source line #179	-> byte code offset #557
/*     */     //   Java source line #180	-> byte code offset #562
/*     */     //   Java source line #183	-> byte code offset #574
/*     */     //   Java source line #184	-> byte code offset #584
/*     */     //   Java source line #185	-> byte code offset #597
/*     */     //   Java source line #186	-> byte code offset #607
/*     */     //   Java source line #188	-> byte code offset #620
/*     */     //   Java source line #189	-> byte code offset #629
/*     */     //   Java source line #190	-> byte code offset #636
/*     */     //   Java source line #192	-> byte code offset #650
/*     */     //   Java source line #195	-> byte code offset #670
/*     */     //   Java source line #196	-> byte code offset #674
/*     */     //   Java source line #197	-> byte code offset #684
/*     */     //   Java source line #198	-> byte code offset #695
/*     */     //   Java source line #199	-> byte code offset #705
/*     */     //   Java source line #200	-> byte code offset #716
/*     */     //   Java source line #201	-> byte code offset #726
/*     */     //   Java source line #205	-> byte code offset #732
/*     */     //   Java source line #206	-> byte code offset #737
/*     */     //   Java source line #208	-> byte code offset #745
/*     */     //   Java source line #209	-> byte code offset #752
/*     */     //   Java source line #211	-> byte code offset #759
/*     */     //   Java source line #212	-> byte code offset #764
/*     */     //   Java source line #214	-> byte code offset #771
/*     */     //   Java source line #217	-> byte code offset #778
/*     */     //   Java source line #222	-> byte code offset #801
/*     */     //   Java source line #223	-> byte code offset #806
/*     */     //   Java source line #225	-> byte code offset #818
/*     */     //   Java source line #227	-> byte code offset #825
/*     */     //   Java source line #231	-> byte code offset #861
/*     */     //   Java source line #233	-> byte code offset #868
/*     */     //   Java source line #235	-> byte code offset #876
/*     */     //   Java source line #236	-> byte code offset #881
/*     */     //   Java source line #237	-> byte code offset #889
/*     */     //   Java source line #240	-> byte code offset #896
/*     */     //   Java source line #242	-> byte code offset #898
/*     */     //   Java source line #246	-> byte code offset #906
/*     */     //   Java source line #248	-> byte code offset #914
/*     */     //   Java source line #253	-> byte code offset #915
/*     */     //   Java source line #254	-> byte code offset #923
/*     */     //   Java source line #255	-> byte code offset #928
/*     */     //   Java source line #261	-> byte code offset #932
/*     */     //   Java source line #263	-> byte code offset #944
/*     */     //   Java source line #264	-> byte code offset #950
/*     */     //   Java source line #400	-> byte code offset #952
/*     */     //   Java source line #404	-> byte code offset #960
/*     */     //   Java source line #406	-> byte code offset #968
/*     */     //   Java source line #265	-> byte code offset #969
/*     */     //   Java source line #268	-> byte code offset #972
/*     */     //   Java source line #270	-> byte code offset #998
/*     */     //   Java source line #271	-> byte code offset #1002
/*     */     //   Java source line #275	-> byte code offset #1009
/*     */     //   Java source line #276	-> byte code offset #1014
/*     */     //   Java source line #278	-> byte code offset #1022
/*     */     //   Java source line #281	-> byte code offset #1027
/*     */     //   Java source line #283	-> byte code offset #1034
/*     */     //   Java source line #287	-> byte code offset #1038
/*     */     //   Java source line #289	-> byte code offset #1049
/*     */     //   Java source line #291	-> byte code offset #1059
/*     */     //   Java source line #293	-> byte code offset #1067
/*     */     //   Java source line #295	-> byte code offset #1072
/*     */     //   Java source line #296	-> byte code offset #1077
/*     */     //   Java source line #297	-> byte code offset #1086
/*     */     //   Java source line #298	-> byte code offset #1092
/*     */     //   Java source line #301	-> byte code offset #1099
/*     */     //   Java source line #302	-> byte code offset #1125
/*     */     //   Java source line #303	-> byte code offset #1136
/*     */     //   Java source line #301	-> byte code offset #1147
/*     */     //   Java source line #306	-> byte code offset #1160
/*     */     //   Java source line #308	-> byte code offset #1165
/*     */     //   Java source line #309	-> byte code offset #1191
/*     */     //   Java source line #310	-> byte code offset #1202
/*     */     //   Java source line #308	-> byte code offset #1213
/*     */     //   Java source line #313	-> byte code offset #1226
/*     */     //   Java source line #315	-> byte code offset #1231
/*     */     //   Java source line #316	-> byte code offset #1240
/*     */     //   Java source line #317	-> byte code offset #1245
/*     */     //   Java source line #320	-> byte code offset #1259
/*     */     //   Java source line #322	-> byte code offset #1264
/*     */     //   Java source line #323	-> byte code offset #1290
/*     */     //   Java source line #322	-> byte code offset #1298
/*     */     //   Java source line #326	-> byte code offset #1311
/*     */     //   Java source line #329	-> byte code offset #1316
/*     */     //   Java source line #330	-> byte code offset #1321
/*     */     //   Java source line #331	-> byte code offset #1331
/*     */     //   Java source line #333	-> byte code offset #1358
/*     */     //   Java source line #334	-> byte code offset #1369
/*     */     //   Java source line #336	-> byte code offset #1402
/*     */     //   Java source line #341	-> byte code offset #1429
/*     */     //   Java source line #342	-> byte code offset #1438
/*     */     //   Java source line #343	-> byte code offset #1443
/*     */     //   Java source line #344	-> byte code offset #1464
/*     */     //   Java source line #343	-> byte code offset #1505
/*     */     //   Java source line #347	-> byte code offset #1518
/*     */     //   Java source line #348	-> byte code offset #1529
/*     */     //   Java source line #350	-> byte code offset #1562
/*     */     //   Java source line #354	-> byte code offset #1592
/*     */     //   Java source line #357	-> byte code offset #1600
/*     */     //   Java source line #361	-> byte code offset #1630
/*     */     //   Java source line #363	-> byte code offset #1635
/*     */     //   Java source line #369	-> byte code offset #1647
/*     */     //   Java source line #376	-> byte code offset #1677
/*     */     //   Java source line #378	-> byte code offset #1688
/*     */     //   Java source line #380	-> byte code offset #1698
/*     */     //   Java source line #383	-> byte code offset #1703
/*     */     //   Java source line #385	-> byte code offset #1709
/*     */     //   Java source line #387	-> byte code offset #1718
/*     */     //   Java source line #389	-> byte code offset #1720
/*     */     //   Java source line #390	-> byte code offset #1722
/*     */     //   Java source line #391	-> byte code offset #1731
/*     */     //   Java source line #400	-> byte code offset #1736
/*     */     //   Java source line #404	-> byte code offset #1744
/*     */     //   Java source line #406	-> byte code offset #1752
/*     */     //   Java source line #393	-> byte code offset #1756
/*     */     //   Java source line #395	-> byte code offset #1758
/*     */     //   Java source line #396	-> byte code offset #1760
/*     */     //   Java source line #400	-> byte code offset #1765
/*     */     //   Java source line #404	-> byte code offset #1773
/*     */     //   Java source line #406	-> byte code offset #1781
/*     */     //   Java source line #399	-> byte code offset #1785
/*     */     //   Java source line #400	-> byte code offset #1787
/*     */     //   Java source line #404	-> byte code offset #1795
/*     */     //   Java source line #406	-> byte code offset #1803
/*     */     //   Java source line #411	-> byte code offset #1804
/*     */     //   Java source line #400	-> byte code offset #1807
/*     */     //   Java source line #404	-> byte code offset #1815
/*     */     //   Java source line #406	-> byte code offset #1823
/*     */     //   Java source line #413	-> byte code offset #1824
/*     */     //   Java source line #414	-> byte code offset #1836
/*     */     // Local variable table:
/*     */     //   start	length	slot	name	signature
/*     */     //   0	1837	0	args	String[]
/*     */     //   1	1034	1	storeFile	boolean
/*     */     //   3	996	2	binaryTransfer	boolean
/*     */     //   5	1820	3	error	boolean
/*     */     //   7	1061	4	listFiles	boolean
/*     */     //   10	1250	5	listNames	boolean
/*     */     //   13	761	6	hidden	boolean
/*     */     //   16	994	7	localActive	boolean
/*     */     //   19	1011	8	useEpsvWithIPv4	boolean
/*     */     //   22	1290	9	feat	boolean
/*     */     //   25	708	10	printHash	boolean
/*     */     //   28	1199	11	mlst	boolean
/*     */     //   31	1130	12	mlsd	boolean
/*     */     //   34	1039	13	lenient	boolean
/*     */     //   39	716	14	keepAliveTimeout	long
/*     */     //   42	725	16	controlKeepAliveReplyTimeout	int
/*     */     //   45	395	17	minParams	int
/*     */     //   48	593	18	protocol	String
/*     */     //   51	1587	19	doCommand	String
/*     */     //   54	665	20	trustmgr	String
/*     */     //   57	493	21	base	int
/*     */     //   435	3	22	remain	int
/*     */     //   463	375	23	server	String
/*     */     //   466	345	24	port	int
/*     */     //   475	16	25	parts	String[]
/*     */     //   506	429	26	username	String
/*     */     //   515	422	27	password	String
/*     */     //   518	1173	28	remote	String
/*     */     //   538	1144	29	local	String
/*     */     //   569	3	30	ftp	org.apache.commons.net.ftp.FTPClient
/*     */     //   672	1144	30	ftp	org.apache.commons.net.ftp.FTPClient
/*     */     //   592	3	31	ftps	org.apache.commons.net.ftp.FTPSClient
/*     */     //   615	3	31	ftps	org.apache.commons.net.ftp.FTPSClient
/*     */     //   645	3	31	ftps	org.apache.commons.net.ftp.FTPSClient
/*     */     //   668	59	31	ftps	org.apache.commons.net.ftp.FTPSClient
/*     */     //   866	3	31	reply	int
/*     */     //   896	28	31	e	java.io.IOException
/*     */     //   1047	13	31	input	java.io.InputStream
/*     */     //   1084	11	31	config	org.apache.commons.net.ftp.FTPClientConfig
/*     */     //   1123	17	31	f	org.apache.commons.net.ftp.FTPFile
/*     */     //   1189	17	31	f	org.apache.commons.net.ftp.FTPFile
/*     */     //   1238	11	31	f	org.apache.commons.net.ftp.FTPFile
/*     */     //   1288	6	31	s	String
/*     */     //   1436	8	31	features	String[]
/*     */     //   1686	13	31	output	java.io.OutputStream
/*     */     //   1718	14	31	e	org.apache.commons.net.ftp.FTPConnectionClosedException
/*     */     //   1756	5	31	e	java.io.IOException
/*     */     //   627	679	32	prot	String[]
/*     */     //   1462	27	32	f	String
/*     */     //   1110	45	33	arrayOfString1	String[]
/*     */     //   1176	45	33	arrayOfString2	String[]
/*     */     //   1275	31	33	arrayOfString3	String[]
/*     */     //   1452	61	33	i	int
/*     */     //   1107	177	34	localObject1	Object
/*     */     //   1449	64	34	j	int
/*     */     //   1446	12	35	arrayOfString4	String[]
/*     */     //   1785	20	36	localObject2	Object
/*     */     //   914	1	57	localIOException1	java.io.IOException
/*     */     //   968	1	58	localIOException2	java.io.IOException
/*     */     //   1752	1	59	localIOException3	java.io.IOException
/*     */     //   1781	1	60	localIOException4	java.io.IOException
/*     */     //   1803	1	61	localIOException5	java.io.IOException
/*     */     //   1823	1	62	localIOException6	java.io.IOException
/*     */     // Exception table:
/*     */     //   from	to	target	type
/*     */     //   801	893	896	java/io/IOException
/*     */     //   906	911	914	java/io/IOException
/*     */     //   960	965	968	java/io/IOException
/*     */     //   932	952	1718	org/apache/commons/net/ftp/FTPConnectionClosedException
/*     */     //   972	1715	1718	org/apache/commons/net/ftp/FTPConnectionClosedException
/*     */     //   1744	1749	1752	java/io/IOException
/*     */     //   932	952	1756	java/io/IOException
/*     */     //   972	1715	1756	java/io/IOException
/*     */     //   1773	1778	1781	java/io/IOException
/*     */     //   932	952	1785	finally
/*     */     //   972	1736	1785	finally
/*     */     //   1756	1765	1785	finally
/*     */     //   1795	1800	1803	java/io/IOException
/*     */     //   1815	1820	1823	java/io/IOException
/*     */   }
/*     */   
/*     */   private static CopyStreamListener createListener()
/*     */   {
/* 417 */     new CopyStreamListener() {
/* 418 */       private long megsTotal = 0L;
/*     */       
/* 420 */       public void bytesTransferred(CopyStreamEvent event) { bytesTransferred(event.getTotalBytesTransferred(), event.getBytesTransferred(), event.getStreamSize()); }
/*     */       
/*     */ 
/*     */       public void bytesTransferred(long totalBytesTransferred, int bytesTransferred, long streamSize)
/*     */       {
/* 425 */         long megs = totalBytesTransferred / 1000000L;
/* 426 */         for (long l = this.megsTotal; l < megs; l += 1L) {
/* 427 */           System.err.print("#");
/*     */         }
/* 429 */         this.megsTotal = megs;
/*     */       }
/*     */     };
/*     */   }
/*     */ }


/* Location:              C:\Users\jiang\Desktop\sexftp-2012.0.0\sexftp_2012.0.0.201202120942.jar!\examples\ftp\FTPClientExample.class
 * Java compiler version: 5 (49.0)
 * JD-Core Version:       0.7.1
 */