package examples.ftp;

public final class TFTPExample {
	static final String USAGE = "Usage: tftp [options] hostname localfile remotefile\n\nhostname   - The name of the remote host\nlocalfile  - The name of the local file to send or the name to use for\n\tthe received file\nremotefile - The name of the remote file to receive or the name for\n\tthe remote server to use to name the local file being sent.\n\noptions: (The default is to assume -r -b)\n\t-s Send a local file\n\t-r Receive a remote file\n\t-a Use ASCII transfer mode\n\t-b Use binary transfer mode\n";

	/* Error */
	public static final void main(String[] args) {
		// Byte code:
		// 0: iconst_1
		// 1: istore_1
		// 2: iconst_1
		// 3: istore_3
		// 4: iconst_0
		// 5: istore 4
		// 7: goto +102 -> 109
		// 10: aload_0
		// 11: iload 4
		// 13: aaload
		// 14: astore 5
		// 16: aload 5
		// 18: ldc 21
		// 20: invokevirtual 23 java/lang/String:startsWith
		// (Ljava/lang/String;)Z
		// 23: ifeq +93 -> 116
		// 26: aload 5
		// 28: ldc 29
		// 30: invokevirtual 31 java/lang/String:equals (Ljava/lang/Object;)Z
		// 33: ifeq +8 -> 41
		// 36: iconst_1
		// 37: istore_1
		// 38: goto +68 -> 106
		// 41: aload 5
		// 43: ldc 35
		// 45: invokevirtual 31 java/lang/String:equals (Ljava/lang/Object;)Z
		// 48: ifeq +8 -> 56
		// 51: iconst_0
		// 52: istore_1
		// 53: goto +53 -> 106
		// 56: aload 5
		// 58: ldc 37
		// 60: invokevirtual 31 java/lang/String:equals (Ljava/lang/Object;)Z
		// 63: ifeq +8 -> 71
		// 66: iconst_0
		// 67: istore_3
		// 68: goto +38 -> 106
		// 71: aload 5
		// 73: ldc 39
		// 75: invokevirtual 31 java/lang/String:equals (Ljava/lang/Object;)Z
		// 78: ifeq +8 -> 86
		// 81: iconst_1
		// 82: istore_3
		// 83: goto +23 -> 106
		// 86: getstatic 41 java/lang/System:err Ljava/io/PrintStream;
		// 89: ldc 47
		// 91: invokevirtual 49 java/io/PrintStream:println
		// (Ljava/lang/String;)V
		// 94: getstatic 41 java/lang/System:err Ljava/io/PrintStream;
		// 97: ldc 8
		// 99: invokevirtual 55 java/io/PrintStream:print (Ljava/lang/String;)V
		// 102: iconst_1
		// 103: invokestatic 58 java/lang/System:exit (I)V
		// 106: iinc 4 1
		// 109: iload 4
		// 111: aload_0
		// 112: arraylength
		// 113: if_icmplt -103 -> 10
		// 116: aload_0
		// 117: arraylength
		// 118: iload 4
		// 120: isub
		// 121: iconst_3
		// 122: if_icmpeq +23 -> 145
		// 125: getstatic 41 java/lang/System:err Ljava/io/PrintStream;
		// 128: ldc 62
		// 130: invokevirtual 49 java/io/PrintStream:println
		// (Ljava/lang/String;)V
		// 133: getstatic 41 java/lang/System:err Ljava/io/PrintStream;
		// 136: ldc 8
		// 138: invokevirtual 55 java/io/PrintStream:print (Ljava/lang/String;)V
		// 141: iconst_1
		// 142: invokestatic 58 java/lang/System:exit (I)V
		// 145: aload_0
		// 146: iload 4
		// 148: aaload
		// 149: astore 6
		// 151: aload_0
		// 152: iload 4
		// 154: iconst_1
		// 155: iadd
		// 156: aaload
		// 157: astore 7
		// 159: aload_0
		// 160: iload 4
		// 162: iconst_2
		// 163: iadd
		// 164: aaload
		// 165: astore 8
		// 167: new 64 org/apache/commons/net/tftp/TFTPClient
		// 170: dup
		// 171: invokespecial 66 org/apache/commons/net/tftp/TFTPClient:<init>
		// ()V
		// 174: astore 9
		// 176: aload 9
		// 178: ldc 67
		// 180: invokevirtual 68
		// org/apache/commons/net/tftp/TFTPClient:setDefaultTimeout (I)V
		// 183: aload 9
		// 185: invokevirtual 71 org/apache/commons/net/tftp/TFTPClient:open ()V
		// 188: goto +28 -> 216
		// 191: astore 10
		// 193: getstatic 41 java/lang/System:err Ljava/io/PrintStream;
		// 196: ldc 74
		// 198: invokevirtual 49 java/io/PrintStream:println
		// (Ljava/lang/String;)V
		// 201: getstatic 41 java/lang/System:err Ljava/io/PrintStream;
		// 204: aload 10
		// 206: invokevirtual 76 java/net/SocketException:getMessage
		// ()Ljava/lang/String;
		// 209: invokevirtual 49 java/io/PrintStream:println
		// (Ljava/lang/String;)V
		// 212: iconst_1
		// 213: invokestatic 58 java/lang/System:exit (I)V
		// 216: iconst_0
		// 217: istore_2
		// 218: iload_1
		// 219: ifeq +361 -> 580
		// 222: aconst_null
		// 223: astore 10
		// 225: new 82 java/io/File
		// 228: dup
		// 229: aload 7
		// 231: invokespecial 84 java/io/File:<init> (Ljava/lang/String;)V
		// 234: astore 11
		// 236: aload 11
		// 238: invokevirtual 86 java/io/File:exists ()Z
		// 241: ifeq +35 -> 276
		// 244: getstatic 41 java/lang/System:err Ljava/io/PrintStream;
		// 247: new 90 java/lang/StringBuilder
		// 250: dup
		// 251: ldc 92
		// 253: invokespecial 94 java/lang/StringBuilder:<init>
		// (Ljava/lang/String;)V
		// 256: aload 7
		// 258: invokevirtual 95 java/lang/StringBuilder:append
		// (Ljava/lang/String;)Ljava/lang/StringBuilder;
		// 261: ldc 99
		// 263: invokevirtual 95 java/lang/StringBuilder:append
		// (Ljava/lang/String;)Ljava/lang/StringBuilder;
		// 266: invokevirtual 101 java/lang/StringBuilder:toString
		// ()Ljava/lang/String;
		// 269: invokevirtual 49 java/io/PrintStream:println
		// (Ljava/lang/String;)V
		// 272: iconst_1
		// 273: invokestatic 58 java/lang/System:exit (I)V
		// 276: new 104 java/io/FileOutputStream
		// 279: dup
		// 280: aload 11
		// 282: invokespecial 106 java/io/FileOutputStream:<init>
		// (Ljava/io/File;)V
		// 285: astore 10
		// 287: goto +33 -> 320
		// 290: astore 12
		// 292: aload 9
		// 294: invokevirtual 109 org/apache/commons/net/tftp/TFTPClient:close
		// ()V
		// 297: getstatic 41 java/lang/System:err Ljava/io/PrintStream;
		// 300: ldc 112
		// 302: invokevirtual 49 java/io/PrintStream:println
		// (Ljava/lang/String;)V
		// 305: getstatic 41 java/lang/System:err Ljava/io/PrintStream;
		// 308: aload 12
		// 310: invokevirtual 114 java/io/IOException:getMessage
		// ()Ljava/lang/String;
		// 313: invokevirtual 49 java/io/PrintStream:println
		// (Ljava/lang/String;)V
		// 316: iconst_1
		// 317: invokestatic 58 java/lang/System:exit (I)V
		// 320: aload 9
		// 322: aload 8
		// 324: iload_3
		// 325: aload 10
		// 327: aload 6
		// 329: invokevirtual 117
		// org/apache/commons/net/tftp/TFTPClient:receiveFile
		// (Ljava/lang/String;ILjava/io/OutputStream;Ljava/lang/String;)I
		// 332: pop
		// 333: goto +193 -> 526
		// 336: astore 12
		// 338: getstatic 41 java/lang/System:err Ljava/io/PrintStream;
		// 341: ldc 121
		// 343: invokevirtual 49 java/io/PrintStream:println
		// (Ljava/lang/String;)V
		// 346: getstatic 41 java/lang/System:err Ljava/io/PrintStream;
		// 349: aload 12
		// 351: invokevirtual 123 java/net/UnknownHostException:getMessage
		// ()Ljava/lang/String;
		// 354: invokevirtual 49 java/io/PrintStream:println
		// (Ljava/lang/String;)V
		// 357: iconst_1
		// 358: invokestatic 58 java/lang/System:exit (I)V
		// 361: aload 9
		// 363: invokevirtual 109 org/apache/commons/net/tftp/TFTPClient:close
		// ()V
		// 366: aload 10
		// 368: ifnull +8 -> 376
		// 371: aload 10
		// 373: invokevirtual 126 java/io/FileOutputStream:close ()V
		// 376: iconst_1
		// 377: istore_2
		// 378: goto +191 -> 569
		// 381: astore 14
		// 383: iconst_0
		// 384: istore_2
		// 385: getstatic 41 java/lang/System:err Ljava/io/PrintStream;
		// 388: ldc 127
		// 390: invokevirtual 49 java/io/PrintStream:println
		// (Ljava/lang/String;)V
		// 393: getstatic 41 java/lang/System:err Ljava/io/PrintStream;
		// 396: aload 14
		// 398: invokevirtual 114 java/io/IOException:getMessage
		// ()Ljava/lang/String;
		// 401: invokevirtual 49 java/io/PrintStream:println
		// (Ljava/lang/String;)V
		// 404: goto +165 -> 569
		// 407: astore 12
		// 409: getstatic 41 java/lang/System:err Ljava/io/PrintStream;
		// 412: ldc -127
		// 414: invokevirtual 49 java/io/PrintStream:println
		// (Ljava/lang/String;)V
		// 417: getstatic 41 java/lang/System:err Ljava/io/PrintStream;
		// 420: aload 12
		// 422: invokevirtual 114 java/io/IOException:getMessage
		// ()Ljava/lang/String;
		// 425: invokevirtual 49 java/io/PrintStream:println
		// (Ljava/lang/String;)V
		// 428: iconst_1
		// 429: invokestatic 58 java/lang/System:exit (I)V
		// 432: aload 9
		// 434: invokevirtual 109 org/apache/commons/net/tftp/TFTPClient:close
		// ()V
		// 437: aload 10
		// 439: ifnull +8 -> 447
		// 442: aload 10
		// 444: invokevirtual 126 java/io/FileOutputStream:close ()V
		// 447: iconst_1
		// 448: istore_2
		// 449: goto +120 -> 569
		// 452: astore 14
		// 454: iconst_0
		// 455: istore_2
		// 456: getstatic 41 java/lang/System:err Ljava/io/PrintStream;
		// 459: ldc 127
		// 461: invokevirtual 49 java/io/PrintStream:println
		// (Ljava/lang/String;)V
		// 464: getstatic 41 java/lang/System:err Ljava/io/PrintStream;
		// 467: aload 14
		// 469: invokevirtual 114 java/io/IOException:getMessage
		// ()Ljava/lang/String;
		// 472: invokevirtual 49 java/io/PrintStream:println
		// (Ljava/lang/String;)V
		// 475: goto +94 -> 569
		// 478: astore 13
		// 480: aload 9
		// 482: invokevirtual 109 org/apache/commons/net/tftp/TFTPClient:close
		// ()V
		// 485: aload 10
		// 487: ifnull +8 -> 495
		// 490: aload 10
		// 492: invokevirtual 126 java/io/FileOutputStream:close ()V
		// 495: iconst_1
		// 496: istore_2
		// 497: goto +26 -> 523
		// 500: astore 14
		// 502: iconst_0
		// 503: istore_2
		// 504: getstatic 41 java/lang/System:err Ljava/io/PrintStream;
		// 507: ldc 127
		// 509: invokevirtual 49 java/io/PrintStream:println
		// (Ljava/lang/String;)V
		// 512: getstatic 41 java/lang/System:err Ljava/io/PrintStream;
		// 515: aload 14
		// 517: invokevirtual 114 java/io/IOException:getMessage
		// ()Ljava/lang/String;
		// 520: invokevirtual 49 java/io/PrintStream:println
		// (Ljava/lang/String;)V
		// 523: aload 13
		// 525: athrow
		// 526: aload 9
		// 528: invokevirtual 109 org/apache/commons/net/tftp/TFTPClient:close
		// ()V
		// 531: aload 10
		// 533: ifnull +8 -> 541
		// 536: aload 10
		// 538: invokevirtual 126 java/io/FileOutputStream:close ()V
		// 541: iconst_1
		// 542: istore_2
		// 543: goto +26 -> 569
		// 546: astore 14
		// 548: iconst_0
		// 549: istore_2
		// 550: getstatic 41 java/lang/System:err Ljava/io/PrintStream;
		// 553: ldc 127
		// 555: invokevirtual 49 java/io/PrintStream:println
		// (Ljava/lang/String;)V
		// 558: getstatic 41 java/lang/System:err Ljava/io/PrintStream;
		// 561: aload 14
		// 563: invokevirtual 114 java/io/IOException:getMessage
		// ()Ljava/lang/String;
		// 566: invokevirtual 49 java/io/PrintStream:println
		// (Ljava/lang/String;)V
		// 569: iload_2
		// 570: ifne +313 -> 883
		// 573: iconst_1
		// 574: invokestatic 58 java/lang/System:exit (I)V
		// 577: goto +306 -> 883
		// 580: aconst_null
		// 581: astore 10
		// 583: new 131 java/io/FileInputStream
		// 586: dup
		// 587: aload 7
		// 589: invokespecial 133 java/io/FileInputStream:<init>
		// (Ljava/lang/String;)V
		// 592: astore 10
		// 594: goto +33 -> 627
		// 597: astore 11
		// 599: aload 9
		// 601: invokevirtual 109 org/apache/commons/net/tftp/TFTPClient:close
		// ()V
		// 604: getstatic 41 java/lang/System:err Ljava/io/PrintStream;
		// 607: ldc -122
		// 609: invokevirtual 49 java/io/PrintStream:println
		// (Ljava/lang/String;)V
		// 612: getstatic 41 java/lang/System:err Ljava/io/PrintStream;
		// 615: aload 11
		// 617: invokevirtual 114 java/io/IOException:getMessage
		// ()Ljava/lang/String;
		// 620: invokevirtual 49 java/io/PrintStream:println
		// (Ljava/lang/String;)V
		// 623: iconst_1
		// 624: invokestatic 58 java/lang/System:exit (I)V
		// 627: aload 9
		// 629: aload 8
		// 631: iload_3
		// 632: aload 10
		// 634: aload 6
		// 636: invokevirtual 136
		// org/apache/commons/net/tftp/TFTPClient:sendFile
		// (Ljava/lang/String;ILjava/io/InputStream;Ljava/lang/String;)V
		// 639: goto +193 -> 832
		// 642: astore 11
		// 644: getstatic 41 java/lang/System:err Ljava/io/PrintStream;
		// 647: ldc 121
		// 649: invokevirtual 49 java/io/PrintStream:println
		// (Ljava/lang/String;)V
		// 652: getstatic 41 java/lang/System:err Ljava/io/PrintStream;
		// 655: aload 11
		// 657: invokevirtual 123 java/net/UnknownHostException:getMessage
		// ()Ljava/lang/String;
		// 660: invokevirtual 49 java/io/PrintStream:println
		// (Ljava/lang/String;)V
		// 663: iconst_1
		// 664: invokestatic 58 java/lang/System:exit (I)V
		// 667: aload 9
		// 669: invokevirtual 109 org/apache/commons/net/tftp/TFTPClient:close
		// ()V
		// 672: aload 10
		// 674: ifnull +8 -> 682
		// 677: aload 10
		// 679: invokevirtual 140 java/io/FileInputStream:close ()V
		// 682: iconst_1
		// 683: istore_2
		// 684: goto +191 -> 875
		// 687: astore 13
		// 689: iconst_0
		// 690: istore_2
		// 691: getstatic 41 java/lang/System:err Ljava/io/PrintStream;
		// 694: ldc 127
		// 696: invokevirtual 49 java/io/PrintStream:println
		// (Ljava/lang/String;)V
		// 699: getstatic 41 java/lang/System:err Ljava/io/PrintStream;
		// 702: aload 13
		// 704: invokevirtual 114 java/io/IOException:getMessage
		// ()Ljava/lang/String;
		// 707: invokevirtual 49 java/io/PrintStream:println
		// (Ljava/lang/String;)V
		// 710: goto +165 -> 875
		// 713: astore 11
		// 715: getstatic 41 java/lang/System:err Ljava/io/PrintStream;
		// 718: ldc -115
		// 720: invokevirtual 49 java/io/PrintStream:println
		// (Ljava/lang/String;)V
		// 723: getstatic 41 java/lang/System:err Ljava/io/PrintStream;
		// 726: aload 11
		// 728: invokevirtual 114 java/io/IOException:getMessage
		// ()Ljava/lang/String;
		// 731: invokevirtual 49 java/io/PrintStream:println
		// (Ljava/lang/String;)V
		// 734: iconst_1
		// 735: invokestatic 58 java/lang/System:exit (I)V
		// 738: aload 9
		// 740: invokevirtual 109 org/apache/commons/net/tftp/TFTPClient:close
		// ()V
		// 743: aload 10
		// 745: ifnull +8 -> 753
		// 748: aload 10
		// 750: invokevirtual 140 java/io/FileInputStream:close ()V
		// 753: iconst_1
		// 754: istore_2
		// 755: goto +120 -> 875
		// 758: astore 13
		// 760: iconst_0
		// 761: istore_2
		// 762: getstatic 41 java/lang/System:err Ljava/io/PrintStream;
		// 765: ldc 127
		// 767: invokevirtual 49 java/io/PrintStream:println
		// (Ljava/lang/String;)V
		// 770: getstatic 41 java/lang/System:err Ljava/io/PrintStream;
		// 773: aload 13
		// 775: invokevirtual 114 java/io/IOException:getMessage
		// ()Ljava/lang/String;
		// 778: invokevirtual 49 java/io/PrintStream:println
		// (Ljava/lang/String;)V
		// 781: goto +94 -> 875
		// 784: astore 12
		// 786: aload 9
		// 788: invokevirtual 109 org/apache/commons/net/tftp/TFTPClient:close
		// ()V
		// 791: aload 10
		// 793: ifnull +8 -> 801
		// 796: aload 10
		// 798: invokevirtual 140 java/io/FileInputStream:close ()V
		// 801: iconst_1
		// 802: istore_2
		// 803: goto +26 -> 829
		// 806: astore 13
		// 808: iconst_0
		// 809: istore_2
		// 810: getstatic 41 java/lang/System:err Ljava/io/PrintStream;
		// 813: ldc 127
		// 815: invokevirtual 49 java/io/PrintStream:println
		// (Ljava/lang/String;)V
		// 818: getstatic 41 java/lang/System:err Ljava/io/PrintStream;
		// 821: aload 13
		// 823: invokevirtual 114 java/io/IOException:getMessage
		// ()Ljava/lang/String;
		// 826: invokevirtual 49 java/io/PrintStream:println
		// (Ljava/lang/String;)V
		// 829: aload 12
		// 831: athrow
		// 832: aload 9
		// 834: invokevirtual 109 org/apache/commons/net/tftp/TFTPClient:close
		// ()V
		// 837: aload 10
		// 839: ifnull +8 -> 847
		// 842: aload 10
		// 844: invokevirtual 140 java/io/FileInputStream:close ()V
		// 847: iconst_1
		// 848: istore_2
		// 849: goto +26 -> 875
		// 852: astore 13
		// 854: iconst_0
		// 855: istore_2
		// 856: getstatic 41 java/lang/System:err Ljava/io/PrintStream;
		// 859: ldc 127
		// 861: invokevirtual 49 java/io/PrintStream:println
		// (Ljava/lang/String;)V
		// 864: getstatic 41 java/lang/System:err Ljava/io/PrintStream;
		// 867: aload 13
		// 869: invokevirtual 114 java/io/IOException:getMessage
		// ()Ljava/lang/String;
		// 872: invokevirtual 49 java/io/PrintStream:println
		// (Ljava/lang/String;)V
		// 875: iload_2
		// 876: ifne +7 -> 883
		// 879: iconst_1
		// 880: invokestatic 58 java/lang/System:exit (I)V
		// 883: return
		// Line number table:
		// Java source line #64 -> byte code offset #0
		// Java source line #65 -> byte code offset #2
		// Java source line #70 -> byte code offset #4
		// Java source line #72 -> byte code offset #10
		// Java source line #73 -> byte code offset #16
		// Java source line #75 -> byte code offset #26
		// Java source line #76 -> byte code offset #36
		// Java source line #77 -> byte code offset #41
		// Java source line #78 -> byte code offset #51
		// Java source line #79 -> byte code offset #56
		// Java source line #80 -> byte code offset #66
		// Java source line #81 -> byte code offset #71
		// Java source line #82 -> byte code offset #81
		// Java source line #85 -> byte code offset #86
		// Java source line #86 -> byte code offset #94
		// Java source line #87 -> byte code offset #102
		// Java source line #70 -> byte code offset #106
		// Java source line #95 -> byte code offset #116
		// Java source line #97 -> byte code offset #125
		// Java source line #98 -> byte code offset #133
		// Java source line #99 -> byte code offset #141
		// Java source line #103 -> byte code offset #145
		// Java source line #104 -> byte code offset #151
		// Java source line #105 -> byte code offset #159
		// Java source line #108 -> byte code offset #167
		// Java source line #111 -> byte code offset #176
		// Java source line #116 -> byte code offset #183
		// Java source line #118 -> byte code offset #191
		// Java source line #120 -> byte code offset #193
		// Java source line #121 -> byte code offset #201
		// Java source line #122 -> byte code offset #212
		// Java source line #126 -> byte code offset #216
		// Java source line #129 -> byte code offset #218
		// Java source line #131 -> byte code offset #222
		// Java source line #134 -> byte code offset #225
		// Java source line #137 -> byte code offset #236
		// Java source line #139 -> byte code offset #244
		// Java source line #140 -> byte code offset #272
		// Java source line #146 -> byte code offset #276
		// Java source line #148 -> byte code offset #290
		// Java source line #150 -> byte code offset #292
		// Java source line #151 -> byte code offset #297
		// Java source line #152 -> byte code offset #305
		// Java source line #153 -> byte code offset #316
		// Java source line #159 -> byte code offset #320
		// Java source line #161 -> byte code offset #336
		// Java source line #163 -> byte code offset #338
		// Java source line #164 -> byte code offset #346
		// Java source line #165 -> byte code offset #357
		// Java source line #177 -> byte code offset #361
		// Java source line #180 -> byte code offset #366
		// Java source line #181 -> byte code offset #371
		// Java source line #183 -> byte code offset #376
		// Java source line #185 -> byte code offset #381
		// Java source line #187 -> byte code offset #383
		// Java source line #188 -> byte code offset #385
		// Java source line #189 -> byte code offset #393
		// Java source line #167 -> byte code offset #407
		// Java source line #169 -> byte code offset #409
		// Java source line #170 -> byte code offset #412
		// Java source line #169 -> byte code offset #414
		// Java source line #171 -> byte code offset #417
		// Java source line #172 -> byte code offset #428
		// Java source line #177 -> byte code offset #432
		// Java source line #180 -> byte code offset #437
		// Java source line #181 -> byte code offset #442
		// Java source line #183 -> byte code offset #447
		// Java source line #185 -> byte code offset #452
		// Java source line #187 -> byte code offset #454
		// Java source line #188 -> byte code offset #456
		// Java source line #189 -> byte code offset #464
		// Java source line #175 -> byte code offset #478
		// Java source line #177 -> byte code offset #480
		// Java source line #180 -> byte code offset #485
		// Java source line #181 -> byte code offset #490
		// Java source line #183 -> byte code offset #495
		// Java source line #185 -> byte code offset #500
		// Java source line #187 -> byte code offset #502
		// Java source line #188 -> byte code offset #504
		// Java source line #189 -> byte code offset #512
		// Java source line #191 -> byte code offset #523
		// Java source line #177 -> byte code offset #526
		// Java source line #180 -> byte code offset #531
		// Java source line #181 -> byte code offset #536
		// Java source line #183 -> byte code offset #541
		// Java source line #185 -> byte code offset #546
		// Java source line #187 -> byte code offset #548
		// Java source line #188 -> byte code offset #550
		// Java source line #189 -> byte code offset #558
		// Java source line #193 -> byte code offset #569
		// Java source line #194 -> byte code offset #573
		// Java source line #200 -> byte code offset #580
		// Java source line #205 -> byte code offset #583
		// Java source line #207 -> byte code offset #597
		// Java source line #209 -> byte code offset #599
		// Java source line #210 -> byte code offset #604
		// Java source line #211 -> byte code offset #612
		// Java source line #212 -> byte code offset #623
		// Java source line #218 -> byte code offset #627
		// Java source line #220 -> byte code offset #642
		// Java source line #222 -> byte code offset #644
		// Java source line #223 -> byte code offset #652
		// Java source line #224 -> byte code offset #663
		// Java source line #236 -> byte code offset #667
		// Java source line #239 -> byte code offset #672
		// Java source line #240 -> byte code offset #677
		// Java source line #242 -> byte code offset #682
		// Java source line #244 -> byte code offset #687
		// Java source line #246 -> byte code offset #689
		// Java source line #247 -> byte code offset #691
		// Java source line #248 -> byte code offset #699
		// Java source line #226 -> byte code offset #713
		// Java source line #228 -> byte code offset #715
		// Java source line #229 -> byte code offset #718
		// Java source line #228 -> byte code offset #720
		// Java source line #230 -> byte code offset #723
		// Java source line #231 -> byte code offset #734
		// Java source line #236 -> byte code offset #738
		// Java source line #239 -> byte code offset #743
		// Java source line #240 -> byte code offset #748
		// Java source line #242 -> byte code offset #753
		// Java source line #244 -> byte code offset #758
		// Java source line #246 -> byte code offset #760
		// Java source line #247 -> byte code offset #762
		// Java source line #248 -> byte code offset #770
		// Java source line #234 -> byte code offset #784
		// Java source line #236 -> byte code offset #786
		// Java source line #239 -> byte code offset #791
		// Java source line #240 -> byte code offset #796
		// Java source line #242 -> byte code offset #801
		// Java source line #244 -> byte code offset #806
		// Java source line #246 -> byte code offset #808
		// Java source line #247 -> byte code offset #810
		// Java source line #248 -> byte code offset #818
		// Java source line #250 -> byte code offset #829
		// Java source line #236 -> byte code offset #832
		// Java source line #239 -> byte code offset #837
		// Java source line #240 -> byte code offset #842
		// Java source line #242 -> byte code offset #847
		// Java source line #244 -> byte code offset #852
		// Java source line #246 -> byte code offset #854
		// Java source line #247 -> byte code offset #856
		// Java source line #248 -> byte code offset #864
		// Java source line #252 -> byte code offset #875
		// Java source line #253 -> byte code offset #879
		// Java source line #257 -> byte code offset #883
		// Local variable table:
		// start length slot name signature
		// 0 884 0 args String[]
		// 1 218 1 receiveFile boolean
		// 217 659 2 closed boolean
		// 3 629 3 transferMode int
		// 5 156 4 argc int
		// 14 58 5 arg String
		// 149 486 6 hostname String
		// 157 431 7 localFilename String
		// 165 465 8 remoteFilename String
		// 174 659 9 tftp org.apache.commons.net.tftp.TFTPClient
		// 191 14 10 e java.net.SocketException
		// 223 314 10 output java.io.FileOutputStream
		// 581 262 10 input java.io.FileInputStream
		// 234 47 11 file java.io.File
		// 597 19 11 e java.io.IOException
		// 642 14 11 e java.net.UnknownHostException
		// 713 14 11 e java.io.IOException
		// 290 19 12 e java.io.IOException
		// 336 14 12 e java.net.UnknownHostException
		// 407 423 12 e java.io.IOException
		// 478 46 13 localObject Object
		// 687 16 13 e java.io.IOException
		// 758 16 13 e java.io.IOException
		// 806 16 13 e java.io.IOException
		// 852 16 13 e java.io.IOException
		// 381 16 14 e java.io.IOException
		// 452 16 14 e java.io.IOException
		// 500 16 14 e java.io.IOException
		// 546 16 14 e java.io.IOException
		// Exception table:
		// from to target type
		// 183 188 191 java/net/SocketException
		// 276 287 290 java/io/IOException
		// 320 333 336 java/net/UnknownHostException
		// 366 378 381 java/io/IOException
		// 320 333 407 java/io/IOException
		// 437 449 452 java/io/IOException
		// 320 361 478 finally
		// 407 432 478 finally
		// 485 497 500 java/io/IOException
		// 531 543 546 java/io/IOException
		// 583 594 597 java/io/IOException
		// 627 639 642 java/net/UnknownHostException
		// 672 684 687 java/io/IOException
		// 627 639 713 java/io/IOException
		// 743 755 758 java/io/IOException
		// 627 667 784 finally
		// 713 738 784 finally
		// 791 803 806 java/io/IOException
		// 837 849 852 java/io/IOException
	}
}
